pipeline_utils/__init__.py
pipeline_utils/check_lines.py
cgap_pipeline_utils-23.0.dist-info/LICENSE
cgap_pipeline_utils-23.0.dist-info/METADATA
cgap_pipeline_utils-23.0.dist-info/WHEEL
cgap_pipeline_utils-23.0.dist-info/top_level.txt
cgap_pipeline_utils-23.0.dist-info/RECORD
